espapp/__init__.py
espapp/daily.py
espapp/esp.py
espapp/data/data.txt
espapp/data/data2.txt
espapp/data/data3.txt
espapp/data/data4.txt
espapp/data/ethtoolpyth.py
espapp/data/log
espapp/data/main_ips.json
espapp/data/main_macs.json
espapp/data/main_names.json
espapp/data/output.txt
espapp/data/output2.txt
espapp/data/temp
wolapp-2.1.2.dist-info/LICENSE
wolapp-2.1.2.dist-info/METADATA
wolapp-2.1.2.dist-info/WHEEL
wolapp-2.1.2.dist-info/entry_points.txt
wolapp-2.1.2.dist-info/top_level.txt
wolapp-2.1.2.dist-info/RECORD
