Metadata-Version: 2.1
Name: wolapp
Version: 2.1.2
Summary: WOL applicaion
Home-page: https://github.com/emb-karan/espapp-pkg
Author: Kratinn.com
Author-email: developer@viriminfotech.com
License: Virim
Platform: Linux
Requires-Python: !=2.7,!=3.0.*,!=3.1.*,!=3.2.*,!=3.3.*,!=3.4.*
Requires-Dist: uuid
Requires-Dist: python-crontab
Requires-Dist: requests
